tempit/__init__.py
tempit/cli.py
tempit/core.py
tempit/models.py
tempit/render.py
tempit/services.py
tempit/shell/init.sh
tempit/storage.py
tempit_manager-1.0.dist-info/LICENSE
tempit_manager-1.0.dist-info/METADATA
tempit_manager-1.0.dist-info/WHEEL
tempit_manager-1.0.dist-info/entry_points.txt
tempit_manager-1.0.dist-info/RECORD
