Metadata-Version: 2.3
Name: tempit-manager
Version: 1.0
Summary: Manage and jump into temporary working directories
Author: Idir Oura
Author-email: idir.oura@protonmail.com
Requires-Python: >=3.10,<3.14
Classifier: Programming Language :: Python :: 3
Classifier: Programming Language :: Python :: 3.10
Classifier: Programming Language :: Python :: 3.11
Classifier: Programming Language :: Python :: 3.12
Classifier: Programming Language :: Python :: 3.13
Requires-Dist: flake8 (>=7.3.0,<8.0.0)
Requires-Dist: humanize
Requires-Dist: mypy (>=1.18.1,<2.0.0)
Requires-Dist: pylint (>=3.3.8,<4.0.0)
Requires-Dist: pytest (>=8.4.2,<9.0.0)
Requires-Dist: ruff (>=0.13.0,<0.14.0)
Requires-Dist: tabulate
Requires-Dist: termcolor
